{
    "JKリンク": [
        "なし"
    ],
    "_updated": "2021-12-02",
    "category": [
        "山"
    ],
    "curation": "https://www.hi.u-tokyo.ac.jp/collection/degitalgallary/ryukyu/data/curation/0001.json",
    "description": [
        ""
    ],
    "image": "https://www.hi.u-tokyo.ac.jp/collection/degitalgallary/ryukyu/data/files/tile/0001",
    "jk": [
        ""
    ],
    "label": "高嶽",
    "latitude": [
        "28.471358"
    ],
    "latlng": [
        "28.471358,129.685412"
    ],
    "longitude": [
        "129.685412"
    ],
    "manifest": "https://www.hi.u-tokyo.ac.jp/collection/degitalgallary/ryukyu/data/iiif/0001/manifest.json",
    "member": "https://www.hi.u-tokyo.ac.jp/collection/degitalgallary/ryukyu/data/iiif/0001/canvas/p1#xywh=42790,10512,114,200",
    "objectID": "10098",
    "thumbnail": "https://www.hi.u-tokyo.ac.jp/collection/degitalgallary/ryukyu/data/files/medium/10098.jpg",
    "リンク": [
        "https://goo.gl/maps/YfLx7VGkunfhzg2L7"
    ],
    "備考": [
        ""
    ],
    "図": [
        "正保琉球国絵図写"
    ],
    "現在の地名": [
        "鹿児島県奄美市笠利町大字川上"
    ],
    "番号": [
        "24"
    ],
    "緯度経度": [
        "あり"
    ]
}